rsaitehu/sampling.py
rsaitehu_sampling-0.0.1.dist-info/METADATA
rsaitehu_sampling-0.0.1.dist-info/WHEEL
rsaitehu_sampling-0.0.1.dist-info/top_level.txt
rsaitehu_sampling-0.0.1.dist-info/RECORD
